<sentence id="1">
  <token id="t1.1" form="«" lemma="«" tag="Fra" >
  </token>
  <token id="t1.2" form="Tes" lemma="ton" tag="DP2CPS" >
  </token>
  <token id="t1.3" form="yeux" lemma="oeil" tag="NCMP000" >
  </token>
  <token id="t1.4" form="de" lemma="de" tag="SP" >
  </token>
  <token id="t1.5" form="saphyrs" lemma="saphyrs" tag="NCMP000" >
  </token>
  <token id="t1.6" form="fendus" lemma="fendre" tag="VMP00PM" wn="01573276-v" >
  </token>
  <token id="t1.7" form="en" lemma="en" tag="SP" >
  </token>
  <token id="t1.8" form="amandes" lemma="amande" tag="NCFP000" wn="07750586-n" >
  </token>
  <token id="t1.9" form="." lemma="." tag="Fp" >
  </token>
  <token id="t1.10" form="»" lemma="»" tag="Frc" >
  </token>
  <token id="t1.11" form="LES_POÈTES" lemma="les_poètes" tag="NP00000" >
  </token>
  <token id="t1.12" form="." lemma="." tag="Fp" >
  </token>
</sentence>
<sentence id="2">
  <token id="t2.1" form="L&apos;" lemma="le" tag="DA0CS0" >
  </token>
  <token id="t2.2" form="intérieur" lemma="intérieur" tag="NCMS000" wn="08588294-n" >
  </token>
  <token id="t2.3" form="de" lemma="de" tag="SP" >
  </token>
  <token id="t2.4" form="cette" lemma="ce" tag="DD0FS0" >
  </token>
  <token id="t2.5" form="boîte" lemma="boîte" tag="NCFS000" wn="02883344-n" >
  </token>
  <token id="t2.6" form="énigmatique" lemma="énigmatique" tag="AQ0CS00" >
  </token>
  <token id="t2.7" form="sembla" lemma="sembler" tag="VMIS3S0" >
  </token>
  <token id="t2.8" form="jeter" lemma="jeter" tag="VMN0000" wn="01192179-v" >
  </token>
  <token id="t2.9" form="mille" lemma="mille" tag="NCMP000" wn="13651218-n" >
  </token>
  <token id="t2.10" form="regards" lemma="regard" tag="NCMP000" wn="03717447-n" >
  </token>
  <token id="t2.11" form="sur" lemma="sur" tag="SP" >
  </token>
  <token id="t2.12" form="le" lemma="le" tag="DA0MS0" >
  </token>
  <token id="t2.13" form="jeune" lemma="jeune" tag="AQ0CS00" wn="01646941-a" >
  </token>
  <token id="t2.14" form="Anglais" lemma="anglais" tag="NP00000" wn="06947032-n" >
  </token>
  <token id="t2.15" form="." lemma="." tag="Fp" >
  </token>
  <token id="t2.16" form="--" lemma="--" tag="Fg" >
  </token>
  <token id="t2.17" form="Voici" lemma="voici" tag="I" >
  </token>
  <token id="t2.18" form="," lemma="," tag="Fc" >
  </token>
  <token id="t2.19" form="certes" lemma="certes" tag="RG" wn="00144722-r" >
  </token>
  <token id="t2.20" form="," lemma="," tag="Fc" >
  </token>
  <token id="t2.21" form="de" lemma="de" tag="DF0CN0" >
  </token>
  <token id="t2.22" form="les" lemma="le" tag="DA0CP0" >
  </token>
  <token id="t2.23" form="yeux" lemma="oeil" tag="NCMP000" >
  </token>
  <token id="t2.24" form="que" lemma="que" tag="PR00000" >
  </token>
  <token id="t2.25" form="jalouseraient" lemma="jalouser" tag="VMIC3P0" >
  </token>
  <token id="t2.26" form="bien" lemma="bien" tag="RG" wn="00008007-r" >
  </token>
  <token id="t2.27" form="de" lemma="de" tag="DF0CN0" >
  </token>
  <token id="t2.28" form="les" lemma="le" tag="DA0CP0" >
  </token>
  <token id="t2.29" form="gazelles" lemma="gazelle" tag="NCFP000" wn="02423022-n" >
  </token>
  <token id="t2.30" form="de" lemma="de" tag="SP" >
  </token>
  <token id="t2.31" form="la" lemma="le" tag="DA0FS0" >
  </token>
  <token id="t2.32" form="vallée" lemma="vallée" tag="NCFS000" wn="09468604-n" >
  </token>
  <token id="t2.33" form="de" lemma="de" tag="SP" >
  </token>
  <token id="t2.34" form="Nourmajad" lemma="nourmajad" tag="NP00000" >
  </token>
  <token id="t2.35" form="," lemma="," tag="Fc" >
  </token>
  <token id="t2.36" form="continuait" lemma="continuer" tag="VMII3S0" wn="02684924-v" >
  </token>
  <token id="t2.37" form="Edison" lemma="edison" tag="NP00000" >
  </token>
  <token id="t2.38" form="." lemma="." tag="Fp" >
  </token>
</sentence>
<sentence id="3">
  <token id="t3.1" form="Ce" lemma="ce" tag="PP0CNN0" >
  </token>
  <token id="t3.2" form="sont" lemma="être" tag="VMIP3P0" wn="02604760-v" >
  </token>
  <token id="t3.3" form="de" lemma="de" tag="DF0CN0" >
  </token>
  <token id="t3.4" form="les" lemma="le" tag="DA0CP0" >
  </token>
  <token id="t3.5" form="joyaux" lemma="joyau" tag="NCMP000" >
  </token>
  <token id="t3.6" form="doués" lemma="douer" tag="VMP00PM" >
  </token>
  <token id="t3.7" form="d&apos;" lemma="de" tag="SP" >
  </token>
  <token id="t3.8" form="une" lemma="un" tag="DI0FS0" >
  </token>
  <token id="t3.9" form="sclérotique" lemma="sclérotique" tag="NCFS000" >
  </token>
  <token id="t3.10" form="si" lemma="si" tag="RG" >
  </token>
  <token id="t3.11" form="pure" lemma="pur" tag="AQ0FS00" wn="00361125-a" >
  </token>
  <token id="t3.12" form="," lemma="," tag="Fc" >
  </token>
  <token id="t3.13" form="d&apos;" lemma="de" tag="SP" >
  </token>
  <token id="t3.14" form="une" lemma="un" tag="DI0FS0" >
  </token>
  <token id="t3.15" form="prunelle" lemma="prunelle" tag="NCFS000" >
  </token>
  <token id="t3.16" form="si" lemma="si" tag="RG" >
  </token>
  <token id="t3.17" form="noyée" lemma="noyer" tag="VMP00SF" >
  </token>
  <token id="t3.18" form="," lemma="," tag="Fc" >
  </token>
  <token id="t3.19" form="qu&apos;" lemma="que" tag="CS" >
  </token>
  <token id="t3.20" form="ils" lemma="ils" tag="PP3MPN0" >
  </token>
  <token id="t3.21" form="en" lemma="en" tag="PP3CN00" >
  </token>
  <token id="t3.22" form="sont" lemma="être" tag="VMIP3P0" wn="02604760-v" >
  </token>
  <token id="t3.23" form="inquiétants" lemma="inquiétant" tag="AQ0MP00" >
  </token>
  <token id="t3.24" form="," lemma="," tag="Fc" >
  </token>
  <token id="t3.25" form="n&apos;" lemma="ne" tag="RN" >
  </token>
  <token id="t3.26" form="est" lemma="être" tag="VMIP3S0" >
  </token>
  <token id="t3.27" form="-ce" lemma="ce" tag="PP0CN00" >
  </token>
  <token id="t3.28" form="pas" lemma="pas" tag="RN" wn="00024073-r" >
  </token>
  <token id="t3.29" form="?" lemma="?" tag="Fit" >
  </token>
</sentence>
<sentence id="4">
  <token id="t4.1" form="L&apos;" lemma="le" tag="DA0CS0" >
  </token>
  <token id="t4.2" form="art" lemma="art" tag="NCMS000" wn="00933420-n" >
  </token>
  <token id="t4.3" form="de" lemma="de" tag="SP" >
  </token>
  <token id="t4.4" form="les" lemma="le" tag="DA0CP0" >
  </token>
  <token id="t4.5" form="grands" lemma="grand" tag="AQ0MP00" wn="01382086-a" >
  </token>
  <token id="t4.6" form="ocularistes" lemma="oculariste" tag="NCCP000" >
  </token>
  <token id="t4.7" form="est" lemma="être" tag="VSIP3S0" wn="02604760-v" >
  </token>
  <token id="t4.8" form="parvenu" lemma="parvenir" tag="VMP00SM" wn="02023107-v" >
  </token>
  <token id="t4.9" form="aujourd&apos;hui" lemma="aujourd&apos;hui" tag="RG" wn="00048268-r" >
  </token>
  <token id="t4.10" form="à" lemma="à" tag="SP" >
  </token>
  <token id="t4.11" form="dépasser" lemma="dépasser" tag="VMN0000" wn="02669477-v" >
  </token>
  <token id="t4.12" form="la" lemma="le" tag="DA0FS0" >
  </token>
  <token id="t4.13" form="Nature" lemma="nature" tag="NP00000" wn="04623113-n" >
  </token>
  <token id="t4.14" form="." lemma="." tag="Fp" >
  </token>
</sentence>
<sentence id="5">
  <token id="t5.1" form="La" lemma="le" tag="DA0FS0" >
  </token>
  <token id="t5.2" form="solennité" lemma="solennité" tag="NCFS000" >
  </token>
  <token id="t5.3" form="de" lemma="de" tag="SP" >
  </token>
  <token id="t5.4" form="ces" lemma="ce" tag="DD0CP0" >
  </token>
  <token id="t5.5" form="yeux" lemma="oeil" tag="NCMP000" >
  </token>
  <token id="t5.6" form="donne" lemma="donner" tag="VMIP1S0" wn="01733477-v" >
  </token>
  <token id="t5.7" form="," lemma="," tag="Fc" >
  </token>
  <token id="t5.8" form="positivement" lemma="positivement" tag="RG" wn="00511573-r" >
  </token>
  <token id="t5.9" form="," lemma="," tag="Fc" >
  </token>
  <token id="t5.10" form="la" lemma="le" tag="DA0FS0" >
  </token>
  <token id="t5.11" form="sensation" lemma="sensation" tag="NCFS000" >
  </token>
  <token id="t5.12" form="de" lemma="de" tag="SP" >
  </token>
  <token id="t5.13" form="l&apos;" lemma="le" tag="DA0CS0" >
  </token>
  <token id="t5.14" form="âme" lemma="âme" tag="NCFS000" >
  </token>
  <token id="t5.15" form="." lemma="." tag="Fp" >
  </token>
</sentence>
<sentence id="6">
  <token id="t6.1" form="L&apos;" lemma="le" tag="DA0CS0" >
  </token>
  <token id="t6.2" form="action" lemma="action" tag="NCFS000" wn="00037396-n" >
  </token>
  <token id="t6.3" form="de" lemma="de" tag="SP" >
  </token>
  <token id="t6.4" form="la" lemma="le" tag="DA0FS0" >
  </token>
  <token id="t6.5" form="photographie" lemma="photographie" tag="NCFS000" wn="03925226-n" >
  </token>
  <token id="t6.6" form="colorante" lemma="colorant" tag="AQ0FS00" >
  </token>
  <token id="t6.7" form="leur" lemma="leur" tag="PP3CPD0" >
  </token>
  <token id="t6.8" form="ajoute" lemma="ajouter" tag="VMIP1S0" wn="00182406-v" >
  </token>
  <token id="t6.9" form="une" lemma="un" tag="DI0FS0" >
  </token>
  <token id="t6.10" form="nuance" lemma="nuance" tag="NCFS000" wn="06606191-n" >
  </token>
  <token id="t6.11" form="personnelle" lemma="personnel" tag="AQ0FS00" wn="01767329-a" >
  </token>
  <token id="t6.12" form=";" lemma=";" tag="Fx" >
  </token>
  <token id="t6.13" form="mais" lemma="mais" tag="CC" >
  </token>
  <token id="t6.14" form="c&apos;" lemma="ce" tag="PPSCNN0" >
  </token>
  <token id="t6.15" form="est" lemma="être" tag="VMIP3S0" wn="02604760-v" >
  </token>
  <token id="t6.16" form="sur" lemma="sur" tag="SP" >
  </token>
  <token id="t6.17" form="l&apos;" lemma="le" tag="DA0CS0" >
  </token>
  <token id="t6.18" form="iris" lemma="iris" tag="NCMN000" >
  </token>
  <token id="t6.19" form="qu&apos;" lemma="que" tag="PR00000" >
  </token>
  <token id="t6.20" form="il" lemma="il" tag="PP3MSN0" >
  </token>
  <token id="t6.21" form="s&apos;" lemma="se" tag="PP3CN00" >
  </token>
  <token id="t6.22" form="agit" lemma="agir" tag="VMIP3S0" wn="02367363-v" >
  </token>
  <token id="t6.23" form="de" lemma="de" tag="SP" >
  </token>
  <token id="t6.24" form="transporter" lemma="transporter" tag="VMN0000" wn="01449974-v" >
  </token>
  <token id="t6.25" form="l&apos;" lemma="le" tag="DA0CS0" >
  </token>
  <token id="t6.26" form="individualité" lemma="individualité" tag="NCFS000" >
  </token>
  <token id="t6.27" form="même" lemma="même" tag="AQ0CS00" wn="02071420-a" >
  </token>
  <token id="t6.28" form="de" lemma="de" tag="SP" >
  </token>
  <token id="t6.29" form="le" lemma="le" tag="DA0MS0" >
  </token>
  <token id="t6.30" form="regard" lemma="regard" tag="NCMS000" wn="03717447-n" >
  </token>
  <token id="t6.31" form="." lemma="." tag="Fp" >
  </token>
  <token id="t6.32" form="--" lemma="--" tag="Fg" >
  </token>
  <token id="t6.33" form="Une" lemma="un" tag="DI0FS0" >
  </token>
  <token id="t6.34" form="question" lemma="question" tag="NCFS000" wn="05814291-n" >
  </token>
  <token id="t6.35" form=":" lemma=":" tag="Fd" >
  </token>
  <token id="t6.36" form="--" lemma="--" tag="Fg" >
  </token>
  <token id="t6.37" form="avez" lemma="avoir" tag="VAIP2P0" >
  </token>
  <token id="t6.38" form="-vous" lemma="vous" tag="PP2CP00" >
  </token>
  <token id="t6.39" form="vu" lemma="voir" tag="VMP00SM" wn="02130160-v" >
  </token>
  <token id="t6.40" form="beaucoup_de" lemma="beaucoup_de" tag="DI0CN0" >
  </token>
  <token id="t6.41" form="beaux" lemma="beau" tag="AQ0MP00" >
  </token>
  <token id="t6.42" form="yeux" lemma="oeil" tag="NCMP000" >
  </token>
  <token id="t6.43" form="de_par" lemma="de_par" tag="SP" >
  </token>
  <token id="t6.44" form="le" lemma="le" tag="DA0MS0" >
  </token>
  <token id="t6.45" form="monde" lemma="monde" tag="NCMS000" wn="09466280-n" >
  </token>
  <token id="t6.46" form="," lemma="," tag="Fc" >
  </token>
  <token id="t6.47" form="milord" lemma="milord" tag="NCMS000" wn="10318802-n" >
  </token>
  <token id="t6.48" form="?" lemma="?" tag="Fit" >
  </token>
  <token id="t6.49" form="--" lemma="--" tag="Fg" >
  </token>
  <token id="t6.50" form="Oui" lemma="oui" tag="RG" >
  </token>
  <token id="t6.51" form="," lemma="," tag="Fc" >
  </token>
  <token id="t6.52" form="dit" lemma="dire" tag="VMIP3S0" >
  </token>
  <token id="t6.53" form="lord" lemma="lord" tag="NCMS000" >
  </token>
  <token id="t6.54" form="Ewald" lemma="ewald" tag="NP00000" >
  </token>
  <token id="t6.55" form=";" lemma=";" tag="Fx" >
  </token>
  <token id="t6.56" form="en" lemma="en" tag="SP" >
  </token>
  <token id="t6.57" form="Abyssinie" lemma="abyssinie" tag="NP00000" >
  </token>
  <token id="t6.58" form="," lemma="," tag="Fc" >
  </token>
  <token id="t6.59" form="surtout" lemma="surtout" tag="RG" wn="00073897-r" >
  </token>
  <token id="t6.60" form="." lemma="." tag="Fp" >
  </token>
  <token id="t6.61" form="--" lemma="--" tag="Fg" >
  </token>
  <token id="t6.62" form="Vous" lemma="vous" tag="PP2CP00" >
  </token>
  <token id="t6.63" form="distinguez" lemma="distinguer" tag="VMIP2P0" wn="00651991-v" >
  </token>
  <token id="t6.64" form="l&apos;" lemma="le" tag="DA0CS0" >
  </token>
  <token id="t6.65" form="éclat" lemma="éclat" tag="NCMS000" >
  </token>
  <token id="t6.66" form="de" lemma="de" tag="SP" >
  </token>
  <token id="t6.67" form="les" lemma="le" tag="DA0CP0" >
  </token>
  <token id="t6.68" form="yeux" lemma="oeil" tag="NCMP000" >
  </token>
  <token id="t6.69" form="de" lemma="de" tag="SP" >
  </token>
  <token id="t6.70" form="la" lemma="le" tag="DA0FS0" >
  </token>
  <token id="t6.71" form="beauté" lemma="beauté" tag="NCFS000" >
  </token>
  <token id="t6.72" form="de" lemma="de" tag="SP" >
  </token>
  <token id="t6.73" form="le" lemma="le" tag="DA0MS0" >
  </token>
  <token id="t6.74" form="regard" lemma="regard" tag="NCMS000" wn="03717447-n" >
  </token>
  <token id="t6.75" form="," lemma="," tag="Fc" >
  </token>
  <token id="t6.76" form="n&apos;" lemma="ne" tag="RN" >
  </token>
  <token id="t6.77" form="est" lemma="être" tag="VMIP3S0" >
  </token>
  <token id="t6.78" form="-ce" lemma="ce" tag="PP0CN00" >
  </token>
  <token id="t6.79" form="pas" lemma="pas" tag="RN" wn="00024073-r" >
  </token>
  <token id="t6.80" form="?" lemma="?" tag="Fit" >
  </token>
  <token id="t6.81" form="reprit" lemma="reprendre" tag="VMIS3S0" wn="02632940-v" >
  </token>
  <token id="t6.82" form="Edison" lemma="edison" tag="NP00000" >
  </token>
  <token id="t6.83" form="." lemma="." tag="Fp" >
  </token>
  <token id="t6.84" form="--" lemma="--" tag="Fg" >
  </token>
  <token id="t6.85" form="Certes" lemma="certes" tag="RG" wn="00144722-r" >
  </token>
  <token id="t6.86" form="!" lemma="!" tag="Fat" >
  </token>
  <token id="t6.87" form="dit" lemma="dire" tag="VMIP3S0" >
  </token>
  <token id="t6.88" form="lord" lemma="lord" tag="NCMS000" >
  </token>
  <token id="t6.89" form="Ewald" lemma="ewald" tag="NP00000" >
  </token>
  <token id="t6.90" form="." lemma="." tag="Fp" >
  </token>
</sentence>
<sentence id="7">
  <token id="t7.1" form="Celle" lemma="celui" tag="PD0FS00" >
  </token>
  <token id="t7.2" form="que" lemma="que" tag="PR00000" >
  </token>
  <token id="t7.3" form="vous" lemma="vous" tag="PP2CP00" >
  </token>
  <token id="t7.4" form="verrez_tout" lemma="voir_tout" tag="VMIF2P0" >
  </token>
  <token id="t7.5" form="à" lemma="à" tag="SP" >
  </token>
  <token id="t7.6" form="l&apos;" lemma="le" tag="DA0CS0" >
  </token>
  <token id="t7.7" form="heure" lemma="heure" tag="NCFS000" wn="15228378-n" >
  </token>
  <token id="t7.8" form="a" lemma="avoir" tag="VMIP3S0" wn="02604760-v" >
  </token>
  <token id="t7.9" form="de" lemma="de" tag="DF0CN0" >
  </token>
  <token id="t7.10" form="les" lemma="le" tag="DA0CP0" >
  </token>
  <token id="t7.11" form="yeux" lemma="oeil" tag="NCMP000" >
  </token>
  <token id="t7.12" form="de" lemma="de" tag="SP" >
  </token>
  <token id="t7.13" form="la" lemma="le" tag="DA0FS0" >
  </token>
  <token id="t7.14" form="plus" lemma="plus" tag="RG" wn="00099341-r" >
  </token>
  <token id="t7.15" form="éclatante" lemma="éclatant" tag="AQ0FS00" >
  </token>
  <token id="t7.16" form="beauté" lemma="beauté" tag="NCFS000" >
  </token>
  <token id="t7.17" form="," lemma="," tag="Fc" >
  </token>
  <token id="t7.18" form="lorsqu&apos;elle" lemma="lorsqu&apos;elle" tag="AQ0FS0" >
  </token>
  <token id="t7.19" form="regarde" lemma="regarder" tag="VMIP1S0" wn="02130160-v" >
  </token>
  <token id="t7.20" form="," lemma="," tag="Fc" >
  </token>
  <token id="t7.21" form="inattentive" lemma="inattentif" tag="AQ0FS00" >
  </token>
  <token id="t7.22" form="," lemma="," tag="Fc" >
  </token>
  <token id="t7.23" form="à" lemma="à" tag="SP" >
  </token>
  <token id="t7.24" form="le" lemma="le" tag="DA0MS0" >
  </token>
  <token id="t7.25" form="loin" lemma="loin" tag="RG" wn="00100883-r" >
  </token>
  <token id="t7.26" form="," lemma="," tag="Fc" >
  </token>
  <token id="t7.27" form="devant" lemma="devant" tag="SP" >
  </token>
  <token id="t7.28" form="elle" lemma="elle" tag="PP3FS00" >
  </token>
  <token id="t7.29" form=":" lemma=":" tag="Fd" >
  </token>
  <token id="t7.30" form="--" lemma="--" tag="Fg" >
  </token>
  <token id="t7.31" form="mais" lemma="mais" tag="CC" >
  </token>
  <token id="t7.32" form="," lemma="," tag="Fc" >
  </token>
  <token id="t7.33" form="lorsque" lemma="lorsque" tag="CS" >
  </token>
  <token id="t7.34" form="son" lemma="son" tag="DP3CSS" >
  </token>
  <token id="t7.35" form="regard" lemma="regard" tag="NCMS000" wn="03717447-n" >
  </token>
  <token id="t7.36" form="porte" lemma="porter" tag="VMIP1S0" wn="01449974-v" >
  </token>
  <token id="t7.37" form="sur" lemma="sur" tag="SP" >
  </token>
  <token id="t7.38" form="quelque_chose" lemma="quelque_chose" tag="PI0MS00" >
  </token>
  <token id="t7.39" form="qu&apos;" lemma="que" tag="CS" >
  </token>
  <token id="t7.40" form="elle" lemma="elle" tag="PP3FS00" >
  </token>
  <token id="t7.41" form="remarque" lemma="remarquer" tag="VMSP1S0" >
  </token>
  <token id="t7.42" form="," lemma="," tag="Fc" >
  </token>
  <token id="t7.43" form="le" lemma="le" tag="DA0MS0" >
  </token>
  <token id="t7.44" form="regard" lemma="regard" tag="NCMS000" wn="03717447-n" >
  </token>
  <token id="t7.45" form="," lemma="," tag="Fc" >
  </token>
  <token id="t7.46" form="hélas" lemma="hélas" tag="I" >
  </token>
  <token id="t7.47" form="," lemma="," tag="Fc" >
  </token>
  <token id="t7.48" form="suffit" lemma="suffire" tag="VMIP3S0" wn="02669789-v" >
  </token>
  <token id="t7.49" form="pour" lemma="pour" tag="SP" >
  </token>
  <token id="t7.50" form="faire" lemma="faire" tag="VMN0000" wn="02604760-v" >
  </token>
  <token id="t7.51" form="oublier" lemma="oublier" tag="VMN0000" >
  </token>
  <token id="t7.52" form="les" lemma="le" tag="DA0CP0" >
  </token>
  <token id="t7.53" form="yeux" lemma="oeil" tag="NCMP000" >
  </token>
  <token id="t7.54" form="." lemma="." tag="Fp" >
  </token>
  <token id="t7.55" form="--" lemma="--" tag="Fg" >
  </token>
  <token id="t7.56" form="Voilà" lemma="voilà" tag="I" >
  </token>
  <token id="t7.57" form="qui" lemma="qui" tag="PR00000" >
  </token>
  <token id="t7.58" form="simplifie" lemma="simplifier" tag="VMIP3S0" wn="00400427-v" >
  </token>
  <token id="t7.59" form="toute" lemma="tout" tag="DI0FS0" >
  </token>
  <token id="t7.60" form="difficulté" lemma="difficulté" tag="NCFS000" wn="05687338-n" >
  </token>
  <token id="t7.61" form="!" lemma="!" tag="Fat" >
  </token>
  <token id="t7.62" form="s&apos;" lemma="se" tag="PP3CN00" >
  </token>
  <token id="t7.63" form="écria" lemma="écrier" tag="VMIS3S0" >
  </token>
  <token id="t7.64" form="Edison" lemma="edison" tag="NP00000" >
  </token>
  <token id="t7.65" form="." lemma="." tag="Fp" >
  </token>
</sentence>
<sentence id="8">
  <token id="t8.1" form="Généralement" lemma="généralement" tag="RG" wn="00106921-r" >
  </token>
  <token id="t8.2" form="l&apos;" lemma="le" tag="DA0CS0" >
  </token>
  <token id="t8.3" form="expression" lemma="expression" tag="NCFS000" wn="07139873-n" >
  </token>
  <token id="t8.4" form="de" lemma="de" tag="SP" >
  </token>
  <token id="t8.5" form="le" lemma="le" tag="DA0MS0" >
  </token>
  <token id="t8.6" form="regard" lemma="regard" tag="NCMS000" wn="03717447-n" >
  </token>
  <token id="t8.7" form="humain" lemma="humain" tag="AQ0MS00" wn="01258617-a" >
  </token>
  <token id="t8.8" form="s&apos;" lemma="se" tag="PP3CN00" >
  </token>
  <token id="t8.9" form="augmente" lemma="augmenter" tag="VMIP3S0" wn="00153263-v" >
  </token>
  <token id="t8.10" form="de" lemma="de" tag="SP" >
  </token>
  <token id="t8.11" form="mille" lemma="mille" tag="NCMP000" wn="13651218-n" >
  </token>
  <token id="t8.12" form="incidences" lemma="incidence" tag="NCFP000" wn="11410625-n" >
  </token>
  <token id="t8.13" form="extérieures" lemma="extérieur" tag="AQ0FP00" wn="00948103-a" >
  </token>
  <token id="t8.14" form="," lemma="," tag="Fc" >
  </token>
  <token id="t8.15" form="--" lemma="--" tag="Fg" >
  </token>
  <token id="t8.16" form="de" lemma="de" tag="SP" >
  </token>
  <token id="t8.17" form="l&apos;" lemma="le" tag="DA0CS0" >
  </token>
  <token id="t8.18" form="imperceptible" lemma="imperceptible" tag="AQ0CS00" wn="01748318-a" >
  </token>
  <token id="t8.19" form="jeu" lemma="jeu" tag="NCMS000" wn="00455599-n" >
  </token>
  <token id="t8.20" form="de" lemma="de" tag="SP" >
  </token>
  <token id="t8.21" form="les" lemma="le" tag="DA0CP0" >
  </token>
  <token id="t8.22" form="paupières" lemma="paupière" tag="NCFP000" wn="05313822-n" >
  </token>
  <token id="t8.23" form="," lemma="," tag="Fc" >
  </token>
  <token id="t8.24" form="de" lemma="de" tag="SP" >
  </token>
  <token id="t8.25" form="l&apos;" lemma="le" tag="DA0CS0" >
  </token>
  <token id="t8.26" form="immobilité" lemma="immobilité" tag="NCFS000" >
  </token>
  <token id="t8.27" form="de" lemma="de" tag="SP" >
  </token>
  <token id="t8.28" form="les" lemma="le" tag="DA0CP0" >
  </token>
  <token id="t8.29" form="sourcils" lemma="sourcil" tag="NCMP000" wn="05313535-n" >
  </token>
  <token id="t8.30" form="," lemma="," tag="Fc" >
  </token>
  <token id="t8.31" form="de" lemma="de" tag="SP" >
  </token>
  <token id="t8.32" form="la" lemma="le" tag="DA0FS0" >
  </token>
  <token id="t8.33" form="longueur" lemma="longueur" tag="NCFS000" wn="05129201-n" >
  </token>
  <token id="t8.34" form="de" lemma="de" tag="SP" >
  </token>
  <token id="t8.35" form="les" lemma="le" tag="DA0CP0" >
  </token>
  <token id="t8.36" form="cils" lemma="cil" tag="NCMP000" wn="05314919-n" >
  </token>
  <token id="t8.37" form="," lemma="," tag="Fc" >
  </token>
  <token id="t8.38" form="--" lemma="--" tag="Fg" >
  </token>
  <token id="t8.39" form="surtout" lemma="surtout" tag="RG" wn="00073897-r" >
  </token>
  <token id="t8.40" form="," lemma="," tag="Fc" >
  </token>
  <token id="t8.41" form="de_ce_que" lemma="de_ce_que" tag="CS" >
  </token>
  <token id="t8.42" form="l&apos;on" lemma="on" tag="PP3CSN0" >
  </token>
  <token id="t8.43" form="dit" lemma="dire" tag="VMIP3S0" >
  </token>
  <token id="t8.44" form="," lemma="," tag="Fc" >
  </token>
  <token id="t8.45" form="de" lemma="de" tag="SP" >
  </token>
  <token id="t8.46" form="la" lemma="le" tag="DA0FS0" >
  </token>
  <token id="t8.47" form="circonstance" lemma="circonstance" tag="NCFS000" wn="13942875-n" >
  </token>
  <token id="t8.48" form="où" lemma="où" tag="PR00000" >
  </token>
  <token id="t8.49" form="l&apos;on" lemma="on" tag="PP3CSN0" >
  </token>
  <token id="t8.50" form="se" lemma="se" tag="PP3CN00" >
  </token>
  <token id="t8.51" form="trouve" lemma="trouver" tag="VMIP1S0" wn="02154508-v" >
  </token>
  <token id="t8.52" form="," lemma="," tag="Fc" >
  </token>
  <token id="t8.53" form="de" lemma="de" tag="SP" >
  </token>
  <token id="t8.54" form="l&apos;" lemma="le" tag="DA0CS0" >
  </token>
  <token id="t8.55" form="entourage" lemma="entourage" tag="NCMS000" wn="08429167-n" >
  </token>
  <token id="t8.56" form="," lemma="," tag="Fc" >
  </token>
  <token id="t8.57" form="même" lemma="même" tag="AQ0CS00" wn="02071420-a" >
  </token>
  <token id="t8.58" form="," lemma="," tag="Fc" >
  </token>
  <token id="t8.59" form="qui" lemma="qui" tag="PR00000" >
  </token>
  <token id="t8.60" form="s&apos;" lemma="se" tag="PP3CN00" >
  </token>
  <token id="t8.61" form="y" lemma="y" tag="PP3CN00" >
  </token>
  <token id="t8.62" form="réfléchit" lemma="réfléchir" tag="VMIP3S0" wn="00630380-v" >
  </token>
  <token id="t8.63" form="." lemma="." tag="Fp" >
  </token>
  <token id="t8.64" form="--" lemma="--" tag="Fg" >
  </token>
  <token id="t8.65" form="Tout" lemma="tout" tag="DI0MS0" >
  </token>
  <token id="t8.66" form="cela" lemma="cela" tag="PD0CS00" >
  </token>
  <token id="t8.67" form="renforce" lemma="renforcer" tag="VMIP3S0" wn="00220869-v" >
  </token>
  <token id="t8.68" form="l&apos;" lemma="le" tag="DA0CS0" >
  </token>
  <token id="t8.69" form="expression" lemma="expression" tag="NCFS000" wn="07139873-n" >
  </token>
  <token id="t8.70" form="naturelle" lemma="naturel" tag="AQ0FS00" wn="01569965-a" >
  </token>
  <token id="t8.71" form="de" lemma="de" tag="SP" >
  </token>
  <token id="t8.72" form="l&apos;" lemma="le" tag="DA0CS0" >
  </token>
  <token id="t8.73" form="oeil" lemma="œil" tag="NCMS000" wn="03442164-n" >
  </token>
  <token id="t8.74" form="--" lemma="--" tag="Fg" >
  </token>
  <token id="t8.75" form="De" lemma="de" tag="SP" >
  </token>
  <token id="t8.76" form="nos" lemma="notre" tag="DP1CPP" >
  </token>
  <token id="t8.77" form="jours" lemma="jour" tag="NCMP000" wn="15155220-n" >
  </token>
  <token id="t8.78" form="," lemma="," tag="Fc" >
  </token>
  <token id="t8.79" form="les" lemma="le" tag="DA0CP0" >
  </token>
  <token id="t8.80" form="femmes" lemma="femme" tag="NCFP000" wn="10787470-n" >
  </token>
  <token id="t8.81" form="bien" lemma="bien" tag="RG" wn="00008007-r" >
  </token>
  <token id="t8.82" form="élevées" lemma="élever" tag="VMP00PF" wn="01210854-a" >
  </token>
  <token id="t8.83" form="," lemma="," tag="Fc" >
  </token>
  <token id="t8.84" form="ont" lemma="avoir" tag="VAIP3P0" wn="02604760-v" >
  </token>
  <token id="t8.85" form="acquis" lemma="acquérir" tag="VMP00PM" wn="02210855-v" >
  </token>
  <token id="t8.86" form="un" lemma="un" tag="DI0MS0" >
  </token>
  <token id="t8.87" form="regard" lemma="regard" tag="NCMS000" wn="03717447-n" >
  </token>
  <token id="t8.88" form="unique" lemma="unique" tag="AQ0CS00" wn="02215087-a" >
  </token>
  <token id="t8.89" form="," lemma="," tag="Fc" >
  </token>
  <token id="t8.90" form="mondain" lemma="mondain" tag="NCMS000" >
  </token>
  <token id="t8.91" form="," lemma="," tag="Fc" >
  </token>
  <token id="t8.92" form="convenu" lemma="convenir" tag="VMP00SM" >
  </token>
  <token id="t8.93" form="," lemma="," tag="Fc" >
  </token>
  <token id="t8.94" form="et" lemma="et" tag="CC" >
  </token>
  <token id="t8.95" form="," lemma="," tag="Fc" >
  </token>
  <token id="t8.96" form="vraiment" lemma="vraiment" tag="RG" >
  </token>
  <token id="t8.97" form="," lemma="," tag="Fc" >
  </token>
  <token id="t8.98" form="charmant" lemma="charmant" tag="AQ0MS00" >
  </token>
  <token id="t8.99" form="(" lemma="(" tag="Fpa" >
  </token>
  <token id="t8.100" form="c&apos;" lemma="ce" tag="PPSCNN0" >
  </token>
  <token id="t8.101" form="est" lemma="être" tag="VMIP3S0" wn="02604760-v" >
  </token>
  <token id="t8.102" form="le" lemma="le" tag="DA0MS0" >
  </token>
  <token id="t8.103" form="mot" lemma="mot" tag="NCMS000" wn="06286395-n" >
  </token>
  <token id="t8.104" form=")" lemma=")" tag="Fpt" >
  </token>
  <token id="t8.105" form="," lemma="," tag="Fc" >
  </token>
  <token id="t8.106" form="où" lemma="où" tag="PR00000" >
  </token>
  <token id="t8.107" form="chacun" lemma="chacun" tag="PI0MN00" >
  </token>
  <token id="t8.108" form="trouve" lemma="trouver" tag="VMIP1S0" wn="02154508-v" >
  </token>
  <token id="t8.109" form="l&apos;" lemma="le" tag="DA0CS0" >
  </token>
  <token id="t8.110" form="expression" lemma="expression" tag="NCFS000" wn="07139873-n" >
  </token>
  <token id="t8.111" form="qu&apos;" lemma="que" tag="PR00000" >
  </token>
  <token id="t8.112" form="il" lemma="il" tag="PP3MSN0" >
  </token>
  <token id="t8.113" form="désire" lemma="désirer" tag="VMIP1S0" wn="01824339-v" >
  </token>
  <token id="t8.114" form="et" lemma="et" tag="CC" >
  </token>
  <token id="t8.115" form="qui" lemma="qui" tag="PR00000" >
  </token>
  <token id="t8.116" form="leur" lemma="leur" tag="PP3CPD0" >
  </token>
  <token id="t8.117" form="permet" lemma="permettre" tag="VMIP3S0" wn="02423183-v" >
  </token>
  <token id="t8.118" form="de" lemma="de" tag="SP" >
  </token>
  <token id="t8.119" form="penser" lemma="penser" tag="VMN0000" wn="00930806-v" >
  </token>
  <token id="t8.120" form="à" lemma="à" tag="SP" >
  </token>
  <token id="t8.121" form="leurs" lemma="leur" tag="DP3CPP" >
  </token>
  <token id="t8.122" form="soucis" lemma="souci" tag="NCMP000" wn="12020507-n" >
  </token>
  <token id="t8.123" form="intimes" lemma="intime" tag="AQ0CP00" >
  </token>
  <token id="t8.124" form="," lemma="," tag="Fc" >
  </token>
  <token id="t8.125" form="sous" lemma="sous" tag="SP" >
  </token>
  <token id="t8.126" form="un" lemma="un" tag="DI0MS0" >
  </token>
  <token id="t8.127" form="air" lemma="air" tag="NCMS000" wn="14841267-n" >
  </token>
  <token id="t8.128" form="d&apos;" lemma="de" tag="SP" >
  </token>
  <token id="t8.129" form="attention" lemma="attention" tag="NCFS000" wn="05702275-n" >
  </token>
  <token id="t8.130" form="profonde" lemma="profond" tag="AQ0FS00" wn="00899226-a" >
  </token>
  <token id="t8.131" form="." lemma="." tag="Fp" >
  </token>
</sentence>
<sentence id="9">
  <token id="t9.1" form="Ce" lemma="ce" tag="DD0MS0" >
  </token>
  <token id="t9.2" form="regard" lemma="regard" tag="NCMS000" wn="03717447-n" >
  </token>
  <token id="t9.3" form="," lemma="," tag="Fc" >
  </token>
  <token id="t9.4" form="on" lemma="on" tag="PP3CSN0" >
  </token>
  <token id="t9.5" form="peut" lemma="pouvoir" tag="VMIP3S0" wn="02604760-v" >
  </token>
  <token id="t9.6" form="le" lemma="le" tag="PP3MSA0" >
  </token>
  <token id="t9.7" form="clicher" lemma="clicher" tag="VMN0000" >
  </token>
  <token id="t9.8" form="," lemma="," tag="Fc" >
  </token>
  <token id="t9.9" form="--" lemma="--" tag="Fg" >
  </token>
  <token id="t9.10" form="puisqu&apos;il" lemma="puisqu&apos;il" tag="NCMS000" >
  </token>
  <token id="t9.11" form="n&apos;" lemma="ne" tag="RN" >
  </token>
  <token id="t9.12" form="est" lemma="être" tag="VMIP3S0" wn="02604760-v" >
  </token>
  <token id="t9.13" form="lui-même" lemma="lui-même" tag="PP3MS00" >
  </token>
  <token id="t9.14" form="qu&apos;" lemma="que" tag="CS" >
  </token>
  <token id="t9.15" form="un" lemma="un" tag="DI0MS0" >
  </token>
  <token id="t9.16" form="cliché" lemma="cliché" tag="NCMS000" >
  </token>
  <token id="t9.17" form="," lemma="," tag="Fc" >
  </token>
  <token id="t9.18" form="--" lemma="--" tag="Fg" >
  </token>
  <token id="t9.19" form="n&apos;" lemma="ne" tag="RN" >
  </token>
  <token id="t9.20" form="est" lemma="être" tag="VMIP3S0" >
  </token>
  <token id="t9.21" form="-il" lemma="il" tag="PP3MS00" >
  </token>
  <token id="t9.22" form="pas" lemma="pas" tag="RN" wn="00024073-r" >
  </token>
  <token id="t9.23" form="vrai" lemma="vrai" tag="AQ0MS00" >
  </token>
  <token id="t9.24" form="?" lemma="?" tag="Fit" >
  </token>
  <token id="t9.25" form="--" lemma="--" tag="Fg" >
  </token>
  <token id="t9.26" form="C&apos;" lemma="ce" tag="PPSCNN0" >
  </token>
  <token id="t9.27" form="est" lemma="être" tag="VMIP3S0" wn="02604760-v" >
  </token>
  <token id="t9.28" form="juste" lemma="juste" tag="AQ0CS00" >
  </token>
  <token id="t9.29" form="," lemma="," tag="Fc" >
  </token>
  <token id="t9.30" form="dit" lemma="dire" tag="VMIP3S0" >
  </token>
  <token id="t9.31" form="," lemma="," tag="Fc" >
  </token>
  <token id="t9.32" form="en" lemma="en" tag="SP" >
  </token>
  <token id="t9.33" form="souriant" lemma="sourire" tag="VMG0000" >
  </token>
  <token id="t9.34" form="," lemma="," tag="Fc" >
  </token>
  <token id="t9.35" form="le" lemma="le" tag="DA0MS0" >
  </token>
  <token id="t9.36" form="jeune" lemma="jeune" tag="AQ0CS00" wn="01646941-a" >
  </token>
  <token id="t9.37" form="homme" lemma="homme" tag="NCMS000" wn="00007846-n" >
  </token>
  <token id="t9.38" form="." lemma="." tag="Fp" >
  </token>
  <token id="t9.39" form="--" lemma="--" tag="Fg" >
  </token>
  <token id="t9.40" form="Mais" lemma="mais" tag="CC" >
  </token>
  <token id="t9.41" form="," lemma="," tag="Fc" >
  </token>
  <token id="t9.42" form="continua" lemma="continuer" tag="VMIS3S0" wn="02684924-v" >
  </token>
  <token id="t9.43" form="l&apos;" lemma="le" tag="DA0CS0" >
  </token>
  <token id="t9.44" form="ingénieur" lemma="ingénieur" tag="NCMS000" wn="09615807-n" >
  </token>
  <token id="t9.45" form="," lemma="," tag="Fc" >
  </token>
  <token id="t9.46" form="il" lemma="il" tag="PP3MSN0" >
  </token>
  <token id="t9.47" form="s&apos;" lemma="se" tag="PP3CN00" >
  </token>
  <token id="t9.48" form="agit" lemma="agir" tag="VMIP3S0" wn="02367363-v" >
  </token>
  <token id="t9.49" form="de" lemma="de" tag="SP" >
  </token>
  <token id="t9.50" form="saisir" lemma="saisir" tag="VMN0000" wn="02023107-v" >
  </token>
  <token id="t9.51" form="," lemma="," tag="Fc" >
  </token>
  <token id="t9.52" form="dans" lemma="dans" tag="SP" >
  </token>
  <token id="t9.53" form="l&apos;" lemma="le" tag="DA0CS0" >
  </token>
  <token id="t9.54" form="expérience" lemma="expérience" tag="NCFS000" wn="07285403-n" >
  </token>
  <token id="t9.55" form="qui" lemma="qui" tag="PR00000" >
  </token>
  <token id="t9.56" form="nous" lemma="nous" tag="PP1CP00" >
  </token>
  <token id="t9.57" form="occupe" lemma="occuper" tag="VMIP1S0" wn="01726172-v" >
  </token>
  <token id="t9.58" form="," lemma="," tag="Fc" >
  </token>
  <token id="t9.59" form="non" lemma="non" tag="RG" wn="00024073-r" >
  </token>
  <token id="t9.60" form="pas" lemma="pas" tag="RN" wn="00024073-r" >
  </token>
  <token id="t9.61" form="l&apos;" lemma="le" tag="DA0CS0" >
  </token>
  <token id="t9.62" form="attention" lemma="attention" tag="NCFS000" wn="05702275-n" >
  </token>
  <token id="t9.63" form="de" lemma="de" tag="SP" >
  </token>
  <token id="t9.64" form="le" lemma="le" tag="DA0MS0" >
  </token>
  <token id="t9.65" form="regard" lemma="regard" tag="NCMS000" wn="03717447-n" >
  </token>
  <token id="t9.66" form="," lemma="," tag="Fc" >
  </token>
  <token id="t9.67" form="mais" lemma="mais" tag="CC" >
  </token>
  <token id="t9.68" form="son" lemma="son" tag="DP3CSS" >
  </token>
  <token id="t9.69" form="VAGUE" lemma="vague" tag="NP00000" wn="10771066-n" >
  </token>
  <token id="t9.70" form="," lemma="," tag="Fc" >
  </token>
  <token id="t9.71" form="à" lemma="à" tag="SP" >
  </token>
  <token id="t9.72" form="le" lemma="le" tag="DA0MS0" >
  </token>
  <token id="t9.73" form="contraire" lemma="contraire" tag="NCMS000" >
  </token>
  <token id="t9.74" form="!" lemma="!" tag="Fat" >
  </token>
</sentence>
<sentence id="10">
  <token id="t10.1" form="Et" lemma="et" tag="CC" >
  </token>
  <token id="t10.2" form="vous" lemma="vous" tag="PP2CP00" >
  </token>
  <token id="t10.3" form="m&apos;" lemma="me" tag="PP1CS00" >
  </token>
  <token id="t10.4" form="avez" lemma="avoir" tag="VAIP2P0" wn="02604760-v" >
  </token>
  <token id="t10.5" form="dit" lemma="dire" tag="VMP00SM" >
  </token>
  <token id="t10.6" form="que" lemma="que" tag="CS" >
  </token>
  <token id="t10.7" form="miss" lemma="miss" tag="NCFN000" >
  </token>
  <token id="t10.8" form="Alicia_Clary" lemma="alicia_clary" tag="NP00000" >
  </token>
  <token id="t10.9" form="regardait" lemma="regarder" tag="VMII3S0" wn="02130160-v" >
  </token>
  <token id="t10.10" form="habituellement" lemma="habituellement" tag="RG" wn="00106921-r" >
  </token>
  <token id="t10.11" form="à_travers" lemma="à_travers" tag="SP" >
  </token>
  <token id="t10.12" form="ses" lemma="son" tag="DP3CPS" >
  </token>
  <token id="t10.13" form="cils" lemma="cil" tag="NCMP000" wn="05314919-n" >
  </token>
  <token id="t10.14" form="." lemma="." tag="Fp" >
  </token>
</sentence>
<sentence id="11">
  <token id="t11.1" form="Eh_bien" lemma="eh_bien" tag="I" >
  </token>
  <token id="t11.2" form="!" lemma="!" tag="Fat" >
  </token>
  <token id="t11.3" form="voici" lemma="voici" tag="I" >
  </token>
  <token id="t11.4" form="comment" lemma="comment" tag="PT00000" >
  </token>
  <token id="t11.5" form="je" lemma="je" tag="PP1CSN0" >
  </token>
  <token id="t11.6" form="vais" lemma="aller" tag="VMIP1S0" wn="01835496-v" >
  </token>
  <token id="t11.7" form="procéder" lemma="procéder" tag="VMN0000" wn="01995549-v" >
  </token>
  <token id="t11.8" form="." lemma="." tag="Fp" >
  </token>
</sentence>
<sentence id="12">
  <token id="t12.1" form="Je" lemma="je" tag="PP1CSN0" >
  </token>
  <token id="t12.2" form="vous" lemma="vous" tag="PP2CP00" >
  </token>
  <token id="t12.3" form="parlais" lemma="parler" tag="VMII1S0" >
  </token>
  <token id="t12.4" form="," lemma="," tag="Fc" >
  </token>
  <token id="t12.5" form="tout_à_l&apos;_heure" lemma="tout_à_l&apos;_heure" tag="RG" >
  </token>
  <token id="t12.6" form="," lemma="," tag="Fc" >
  </token>
  <token id="t12.7" form="de" lemma="de" tag="SP" >
  </token>
  <token id="t12.8" form="le" lemma="le" tag="DA0MS0" >
  </token>
  <token id="t12.9" form="phénomène" lemma="phénomène" tag="NCMS000" wn="00034213-n" >
  </token>
  <token id="t12.10" form="récemment" lemma="récemment" tag="RG" wn="00107416-r" >
  </token>
  <token id="t12.11" form="constaté" lemma="constater" tag="VMP00SM" wn="02154508-v" >
  </token>
  <token id="t12.12" form="de" lemma="de" tag="SP" >
  </token>
  <token id="t12.13" form="l&apos;" lemma="le" tag="DA0CS0" >
  </token>
  <token id="t12.14" form="état" lemma="état" tag="NCMS000" wn="00024720-n" >
  </token>
  <token id="t12.15" form="radiant" lemma="radier" tag="VMG0000" >
  </token>
  <token id="t12.16" form="de" lemma="de" tag="SP" >
  </token>
  <token id="t12.17" form="la" lemma="le" tag="DA0FS0" >
  </token>
  <token id="t12.18" form="Matière" lemma="matière" tag="NP00000" wn="05814291-n" >
  </token>
  <token id="t12.19" form=":" lemma=":" tag="Fd" >
  </token>
  <token id="t12.20" form="étant" lemma="être" tag="VSG0000" wn="02604760-v" >
  </token>
  <token id="t12.21" form="donné" lemma="donner" tag="VMP00SM" wn="01733477-v" >
  </token>
  <token id="t12.22" form="le" lemma="le" tag="DA0MS0" >
  </token>
  <token id="t12.23" form="vide" lemma="vide" tag="NCMS000" wn="13910116-n" >
  </token>
  <token id="t12.24" form="le_plus" lemma="le_plus" tag="RG" >
  </token>
  <token id="t12.25" form="parfait" lemma="parfait" tag="AQ0MS00" >
  </token>
  <token id="t12.26" form="," lemma="," tag="Fc" >
  </token>
  <token id="t12.27" form="presque" lemma="presque" tag="RG" wn="00073033-r" >
  </token>
  <token id="t12.28" form="absolu" lemma="absolu" tag="AQ0MS00" >
  </token>
  <token id="t12.29" form="," lemma="," tag="Fc" >
  </token>
  <token id="t12.30" form="que" lemma="que" tag="CS" >
  </token>
  <token id="t12.31" form="l&apos;on" lemma="on" tag="PP3CSN0" >
  </token>
  <token id="t12.32" form="puisse" lemma="pouvoir" tag="VMSP3S0" wn="02604760-v" >
  </token>
  <token id="t12.33" form="produire" lemma="produire" tag="VMN0000" wn="01621555-v" >
  </token>
  <token id="t12.34" form="(" lemma="(" tag="Fpa" >
  </token>
  <token id="t12.35" form="vide" lemma="vide" tag="NCMS000" wn="13910116-n" >
  </token>
  <token id="t12.36" form="obtenu" lemma="obtenir" tag="VMP00SM" wn="01621555-v" >
  </token>
  <token id="t12.37" form="dans" lemma="dans" tag="SP" >
  </token>
  <token id="t12.38" form="tel" lemma="tel" tag="DI0MS0" >
  </token>
  <token id="t12.39" form="sphéroïde" lemma="sphéroïde" tag="NCMS000" wn="13898645-n" >
  </token>
  <token id="t12.40" form="dont" lemma="dont" tag="PR00000" >
  </token>
  <token id="t12.41" form="l&apos;" lemma="le" tag="DA0CS0" >
  </token>
  <token id="t12.42" form="air" lemma="air" tag="NCMS000" wn="14841267-n" >
  </token>
  <token id="t12.43" form="intérieur" lemma="intérieur" tag="AQ0MS00" wn="00950272-a" >
  </token>
  <token id="t12.44" form="a" lemma="avoir" tag="VAIP3S0" wn="02604760-v" >
  </token>
  <token id="t12.45" form="été" lemma="être" tag="VSP00NC" wn="02604760-v" >
  </token>
  <token id="t12.46" form="soumis" lemma="soumettre" tag="VMP00NM" wn="00669762-v" >
  </token>
  <token id="t12.47" form="à" lemma="à" tag="SP" >
  </token>
  <token id="t12.48" form="une" lemma="un" tag="DI0FS0" >
  </token>
  <token id="t12.49" form="température" lemma="température" tag="NCFS000" wn="05011790-n" >
  </token>
  <token id="t12.50" form="d&apos;" lemma="de" tag="SP" >
  </token>
  <token id="t12.51" form="une" lemma="un" tag="DI0FS0" >
  </token>
  <token id="t12.52" form="élévation" lemma="élévation" tag="NCFS000" >
  </token>
  <token id="t12.53" form="souveraine" lemma="souverain" tag="AQ0FS00" >
  </token>
  <token id="t12.54" form=")" lemma=")" tag="Fpt" >
  </token>
  <token id="t12.55" form="," lemma="," tag="Fc" >
  </token>
  <token id="t12.56" form="il" lemma="il" tag="PP3MSN0" >
  </token>
  <token id="t12.57" form="est" lemma="être" tag="VSIP3S0" wn="02604760-v" >
  </token>
  <token id="t12.58" form="avéré" lemma="avérer" tag="VMP00SM" >
  </token>
  <token id="t12.59" form="qu&apos;" lemma="que" tag="CS" >
  </token>
  <token id="t12.60" form="il" lemma="il" tag="PP3MSN0" >
  </token>
  <token id="t12.61" form="peut" lemma="pouvoir" tag="VMIP3S0" wn="02604760-v" >
  </token>
  <token id="t12.62" form="se" lemma="se" tag="PP3CN00" >
  </token>
  <token id="t12.63" form="révéler" lemma="révéler" tag="VMN0000" wn="02143283-v" >
  </token>
  <token id="t12.64" form="," lemma="," tag="Fc" >
  </token>
  <token id="t12.65" form="en" lemma="en" tag="SP" >
  </token>
  <token id="t12.66" form="ce" lemma="ce" tag="DD0MS0" >
  </token>
  <token id="t12.67" form="vide" lemma="vide" tag="NCMS000" wn="13910116-n" >
  </token>
  <token id="t12.68" form="aussi" lemma="aussi" tag="RG" wn="00047534-r" >
  </token>
  <token id="t12.69" form="abstrait" lemma="abstraire" tag="VMP00SM" >
  </token>
  <token id="t12.70" form="que" lemma="que" tag="CS" >
  </token>
  <token id="t12.71" form="possible" lemma="possible" tag="AQ0CS00" wn="01821266-a" >
  </token>
  <token id="t12.72" form="," lemma="," tag="Fc" >
  </token>
  <token id="t12.73" form="de" lemma="de" tag="DF0CN0" >
  </token>
  <token id="t12.74" form="les" lemma="le" tag="DA0CP0" >
  </token>
  <token id="t12.75" form="mouvements" lemma="mouvement" tag="NCMP000" wn="00331950-n" >
  </token>
  <token id="t12.76" form="dus" lemma="devoir" tag="VMIS1S0" wn="01189113-v" >
  </token>
  <token id="t12.77" form="à" lemma="à" tag="SP" >
  </token>
  <token id="t12.78" form="la" lemma="le" tag="DA0FS0" >
  </token>
  <token id="t12.79" form="présence" lemma="présence" tag="NCFS000" wn="13957601-n" >
  </token>
  <token id="t12.80" form="d&apos;" lemma="de" tag="SP" >
  </token>
  <token id="t12.81" form="une" lemma="un" tag="DI0FS0" >
  </token>
  <token id="t12.82" form="Matière" lemma="matière" tag="NP00000" wn="05814291-n" >
  </token>
  <token id="t12.83" form="insaisissable" lemma="insaisissable" tag="AQ0CS00" >
  </token>
  <token id="t12.84" form="." lemma="." tag="Fp" >
  </token>
</sentence>
<sentence id="13">
  <token id="t13.1" form="De" lemma="de" tag="DF0CN0" >
  </token>
  <token id="t13.2" form="les" lemma="le" tag="DA0CP0" >
  </token>
  <token id="t13.3" form="tiges" lemma="tige" tag="NCFP000" wn="13129165-n" >
  </token>
  <token id="t13.4" form="d&apos;" lemma="de" tag="SP" >
  </token>
  <token id="t13.5" form="induction" lemma="induction" tag="NCFS000" wn="05774415-n" >
  </token>
  <token id="t13.6" form="étant" lemma="être" tag="VSG0000" wn="02604760-v" >
  </token>
  <token id="t13.7" form="soudées" lemma="souder" tag="VMP00PF" >
  </token>
  <token id="t13.8" form="à" lemma="à" tag="SP" >
  </token>
  <token id="t13.9" form="les" lemma="le" tag="DA0CP0" >
  </token>
  <token id="t13.10" form="parois" lemma="paroi" tag="NCFP000" wn="04546855-n" >
  </token>
  <token id="t13.11" form="de" lemma="de" tag="SP" >
  </token>
  <token id="t13.12" form="le" lemma="le" tag="DA0MS0" >
  </token>
  <token id="t13.13" form="sphéroïde" lemma="sphéroïde" tag="NCMS000" wn="13898645-n" >
  </token>
  <token id="t13.14" form="," lemma="," tag="Fc" >
  </token>
  <token id="t13.15" form="l&apos;" lemma="le" tag="DA0CS0" >
  </token>
  <token id="t13.16" form="étincelle" lemma="étincelle" tag="NCFS000" wn="11309613-n" >
  </token>
  <token id="t13.17" form="vibre" lemma="vibrer" tag="VMIP3S0" >
  </token>
  <token id="t13.18" form="dans" lemma="dans" tag="SP" >
  </token>
  <token id="t13.19" form="ce" lemma="ce" tag="DD0MS0" >
  </token>
  <token id="t13.20" form="vide" lemma="vide" tag="NCMS000" wn="13910116-n" >
  </token>
  <token id="t13.21" form="," lemma="," tag="Fc" >
  </token>
  <token id="t13.22" form="--" lemma="--" tag="Fg" >
  </token>
  <token id="t13.23" form="et" lemma="et" tag="CC" >
  </token>
  <token id="t13.24" form="l&apos;on" lemma="on" tag="PP3CSN0" >
  </token>
  <token id="t13.25" form="peut" lemma="pouvoir" tag="VMIP3S0" wn="02604760-v" >
  </token>
  <token id="t13.26" form="penser" lemma="penser" tag="VMN0000" wn="00930806-v" >
  </token>
  <token id="t13.27" form="que" lemma="que" tag="CS" >
  </token>
  <token id="t13.28" form="le" lemma="le" tag="DA0MS0" >
  </token>
  <token id="t13.29" form="Commencement" lemma="commencement" tag="NP00000" wn="07323922-n" >
  </token>
  <token id="t13.30" form="de" lemma="de" tag="SP" >
  </token>
  <token id="t13.31" form="le" lemma="le" tag="DA0MS0" >
  </token>
  <token id="t13.32" form="Mouvement" lemma="mouvement" tag="NP00000" wn="00331950-n" >
  </token>
  <token id="t13.33" form="physique" lemma="physique" tag="AQ0CS00" >
  </token>
  <token id="t13.34" form="est" lemma="être" tag="VMIP3S0" wn="02604760-v" >
  </token>
  <token id="t13.35" form="là" lemma="là" tag="RG" >
  </token>
  <token id="t13.36" form="." lemma="." tag="Fp" >
  </token>
</sentence>
<sentence id="14">
  <token id="t14.1" form="Or" lemma="or" tag="CC" >
  </token>
  <token id="t14.2" form="," lemma="," tag="Fc" >
  </token>
  <token id="t14.3" form="voici" lemma="voici" tag="I" >
  </token>
  <token id="t14.4" form="de" lemma="de" tag="SP" >
  </token>
  <token id="t14.5" form="les" lemma="le" tag="DA0CP0" >
  </token>
  <token id="t14.6" form="Yeux" lemma="yeux" tag="NP00000" >
  </token>
  <token id="t14.7" form="fictifs" lemma="fictif" tag="AQ0MP00" >
  </token>
  <token id="t14.8" form="," lemma="," tag="Fc" >
  </token>
  <token id="t14.9" form="ovoïdes" lemma="ovoïde" tag="AQ0CP00" >
  </token>
  <token id="t14.10" form="," lemma="," tag="Fc" >
  </token>
  <token id="t14.11" form="et" lemma="et" tag="CC" >
  </token>
  <token id="t14.12" form="d&apos;" lemma="de" tag="SP" >
  </token>
  <token id="t14.13" form="une" lemma="un" tag="DI0FS0" >
  </token>
  <token id="t14.14" form="transparence" lemma="transparence" tag="NCFS000" wn="11520619-n" >
  </token>
  <token id="t14.15" form="de" lemma="de" tag="SP" >
  </token>
  <token id="t14.16" form="source" lemma="source" tag="NCFS000" wn="08507558-n" >
  </token>
  <token id="t14.17" form="." lemma="." tag="Fp" >
  </token>
</sentence>
<sentence id="15">
  <token id="t15.1" form="J&apos;" lemma="je" tag="PP1CSN0" >
  </token>
  <token id="t15.2" form="y" lemma="y" tag="PP3CN00" >
  </token>
  <token id="t15.3" form="trouverai" lemma="trouver" tag="VMIF1S0" wn="02154508-v" >
  </token>
  <token id="t15.4" form="," lemma="," tag="Fc" >
  </token>
  <token id="t15.5" form="certes" lemma="certes" tag="RG" wn="00144722-r" >
  </token>
  <token id="t15.6" form="," lemma="," tag="Fc" >
  </token>
  <token id="t15.7" form="la" lemma="le" tag="DA0FS0" >
  </token>
  <token id="t15.8" form="paire" lemma="paire" tag="NCFS000" wn="13743605-n" >
  </token>
  <token id="t15.9" form="analogue" lemma="analogue" tag="AQ0CS00" wn="02071420-a" >
  </token>
  <token id="t15.10" form="à" lemma="à" tag="SP" >
  </token>
  <token id="t15.11" form="les" lemma="le" tag="DA0CP0" >
  </token>
  <token id="t15.12" form="yeux" lemma="oeil" tag="NCMP000" >
  </token>
  <token id="t15.13" form="de" lemma="de" tag="SP" >
  </token>
  <token id="t15.14" form="votre" lemma="votre" tag="DP2CSP" >
  </token>
  <token id="t15.15" form="amie" lemma="ami" tag="NCFS000" wn="09679708-n" >
  </token>
  <token id="t15.16" form="." lemma="." tag="Fp" >
  </token>
</sentence>
<sentence id="16">
  <token id="t16.1" form="Une" lemma="un" tag="DI0FS0" >
  </token>
  <token id="t16.2" form="fois" lemma="fois" tag="NCFN000" >
  </token>
  <token id="t16.3" form="relevé" lemma="relever" tag="VMP00SM" wn="02729963-v" >
  </token>
  <token id="t16.4" form="," lemma="," tag="Fc" >
  </token>
  <token id="t16.5" form="en" lemma="en" tag="SP" >
  </token>
  <token id="t16.6" form="leurs" lemma="leur" tag="DP3CPP" >
  </token>
  <token id="t16.7" form="prunelles" lemma="prunelle" tag="NCFP000" >
  </token>
  <token id="t16.8" form="," lemma="," tag="Fc" >
  </token>
  <token id="t16.9" form="ce_que" lemma="ce_que" tag="CS" >
  </token>
  <token id="t16.10" form="les" lemma="le" tag="DA0CP0" >
  </token>
  <token id="t16.11" form="peintres" lemma="peintre" tag="NCCP000" >
  </token>
  <token id="t16.12" form="appellent" lemma="appeler" tag="VMIP3P0" >
  </token>
  <token id="t16.13" form="le" lemma="le" tag="DA0MS0" >
  </token>
  <token id="t16.14" form="point" lemma="point" tag="NCMS000" wn="05865998-n" >
  </token>
  <token id="t16.15" form="visuel" lemma="visuel" tag="AQ0MS00" >
  </token>
  <token id="t16.16" form="," lemma="," tag="Fc" >
  </token>
  <token id="t16.17" form="--" lemma="--" tag="Fg" >
  </token>
  <token id="t16.18" form="comme" lemma="comme" tag="CS" >
  </token>
  <token id="t16.19" form="l&apos;" lemma="le" tag="DA0CS0" >
  </token>
  <token id="t16.20" form="intérieur" lemma="intérieur" tag="NCMS000" wn="08588294-n" >
  </token>
  <token id="t16.21" form="en" lemma="en" tag="PP3CN00" >
  </token>
  <token id="t16.22" form="aura" lemma="avoir" tag="VAIF3S0" wn="02604760-v" >
  </token>
  <token id="t16.23" form="été" lemma="être" tag="VSP00NC" wn="02604760-v" >
  </token>
  <token id="t16.24" form="soumis" lemma="soumettre" tag="VMP00NM" wn="00669762-v" >
  </token>
  <token id="t16.25" form="," lemma="," tag="Fc" >
  </token>
  <token id="t16.26" form="à" lemma="à" tag="SP" >
  </token>
  <token id="t16.27" form="la" lemma="le" tag="DA0FS0" >
  </token>
  <token id="t16.28" form="température" lemma="température" tag="NCFS000" wn="05011790-n" >
  </token>
  <token id="t16.29" form="nécessaire" lemma="nécessaire" tag="AQ0CS00" wn="01580050-a" >
  </token>
  <token id="t16.30" form="pour" lemma="pour" tag="SP" >
  </token>
  <token id="t16.31" form="y" lemma="y" tag="PP3CN00" >
  </token>
  <token id="t16.32" form="opérer" lemma="opérer" tag="VMN0000" wn="00083809-v" >
  </token>
  <token id="t16.33" form="le" lemma="le" tag="DA0MS0" >
  </token>
  <token id="t16.34" form="vide" lemma="vide" tag="NCMS000" wn="13910116-n" >
  </token>
  <token id="t16.35" form="précité" lemma="préciter" tag="VMP00SM" >
  </token>
  <token id="t16.36" form="," lemma="," tag="Fc" >
  </token>
  <token id="t16.37" form="--" lemma="--" tag="Fg" >
  </token>
  <token id="t16.38" form="au_centre" lemma="au_centre" tag="RG" >
  </token>
  <token id="t16.39" form="de" lemma="de" tag="SP" >
  </token>
  <token id="t16.40" form="les" lemma="le" tag="DA0CP0" >
  </token>
  <token id="t16.41" form="prunelles" lemma="prunelle" tag="NCFP000" >
  </token>
  <token id="t16.42" form="," lemma="," tag="Fc" >
  </token>
  <token id="t16.43" form="à" lemma="à" tag="SP" >
  </token>
  <token id="t16.44" form="l&apos;" lemma="le" tag="DA0CS0" >
  </token>
  <token id="t16.45" form="extrémité" lemma="extrémité" tag="NCFS000" wn="08566028-n" >
  </token>
  <token id="t16.46" form="d&apos;" lemma="de" tag="SP" >
  </token>
  <token id="t16.47" form="un" lemma="un" tag="DI0MS0" >
  </token>
  <token id="t16.48" form="inducteur" lemma="inducteur" tag="NCMS000" >
  </token>
  <token id="t16.49" form="de" lemma="de" tag="SP" >
  </token>
  <token id="t16.50" form="la" lemma="le" tag="DA0FS0" >
  </token>
  <token id="t16.51" form="capillarité" lemma="capillarité" tag="NCFS000" wn="11433806-n" >
  </token>
  <token id="t16.52" form="la" lemma="le" tag="DA0FS0" >
  </token>
  <token id="t16.53" form="plus" lemma="plus" tag="RG" wn="00099341-r" >
  </token>
  <token id="t16.54" form="extrême" lemma="extrême" tag="AQ0CS00" wn="00841934-a" >
  </token>
  <token id="t16.55" form="," lemma="," tag="Fc" >
  </token>
  <token id="t16.56" form="je" lemma="je" tag="PP1CSN0" >
  </token>
  <token id="t16.57" form="ferai" lemma="faire" tag="VMIF1S0" wn="02604760-v" >
  </token>
  <token id="t16.58" form="briller" lemma="briller" tag="VMN0000" >
  </token>
  <token id="t16.59" form="," lemma="," tag="Fc" >
  </token>
  <token id="t16.60" form="en" lemma="en" tag="SP" >
  </token>
  <token id="t16.61" form="ce" lemma="ce" tag="DD0MS0" >
  </token>
  <token id="t16.62" form="vide" lemma="vide" tag="NCMS000" wn="13910116-n" >
  </token>
  <token id="t16.63" form="," lemma="," tag="Fc" >
  </token>
  <token id="t16.64" form="la" lemma="le" tag="DA0FS0" >
  </token>
  <token id="t16.65" form="piqûre" lemma="piqûre" tag="NCFS000" >
  </token>
  <token id="t16.66" form="d&apos;" lemma="de" tag="SP" >
  </token>
  <token id="t16.67" form="éclair" lemma="éclair" tag="NCMS000" wn="07628691-n" >
  </token>
  <token id="t16.68" form="," lemma="," tag="Fc" >
  </token>
  <token id="t16.69" form="--" lemma="--" tag="Fg" >
  </token>
  <token id="t16.70" form="mais" lemma="mais" tag="CC" >
  </token>
  <token id="t16.71" form="vague" lemma="vague" tag="AQ0CS00" >
  </token>
  <token id="t16.72" form="et" lemma="et" tag="CC" >
  </token>
  <token id="t16.73" form="presque" lemma="presque" tag="RG" wn="00073033-r" >
  </token>
  <token id="t16.74" form="invisible" lemma="invisible" tag="AQ0CS00" >
  </token>
  <token id="t16.75" form="," lemma="," tag="Fc" >
  </token>
  <token id="t16.76" form="--" lemma="--" tag="Fg" >
  </token>
  <token id="t16.77" form="de" lemma="de" tag="SP" >
  </token>
  <token id="t16.78" form="l&apos;" lemma="le" tag="DA0CS0" >
  </token>
  <token id="t16.79" form="Électricité" lemma="électricité" tag="NP00000" wn="11450566-n" >
  </token>
  <token id="t16.80" form=":" lemma=":" tag="Fd" >
  </token>
  <token id="t16.81" form="le" lemma="le" tag="DA0MS0" >
  </token>
  <token id="t16.82" form="merveilleux" lemma="merveilleux" tag="AQ0MN00" wn="01676517-a" >
  </token>
  <token id="t16.83" form="travail" lemma="travail" tag="NCMS000" wn="00620752-n" >
  </token>
  <token id="t16.84" form="de" lemma="de" tag="SP" >
  </token>
  <token id="t16.85" form="l&apos;" lemma="le" tag="DA0CS0" >
  </token>
  <token id="t16.86" form="iris" lemma="iris" tag="NCMN000" >
  </token>
  <token id="t16.87" form="confère" lemma="conférer" tag="VMIP1S0" wn="02263346-v" >
  </token>
  <token id="t16.88" form="à" lemma="à" tag="SP" >
  </token>
  <token id="t16.89" form="cette" lemma="ce" tag="DD0FS0" >
  </token>
  <token id="t16.90" form="piqûre-vive" lemma="piqûre-vive" tag="AQ0FS0" >
  </token>
  <token id="t16.91" form="l&apos;" lemma="le" tag="DA0CS0" >
  </token>
  <token id="t16.92" form="illusion" lemma="illusion" tag="NCFS000" >
  </token>
  <token id="t16.93" form="totale" lemma="total" tag="AQ0FS00" wn="00515380-a" >
  </token>
  <token id="t16.94" form="de" lemma="de" tag="SP" >
  </token>
  <token id="t16.95" form="la" lemma="le" tag="DA0FS0" >
  </token>
  <token id="t16.96" form="personnalité" lemma="personnalité" tag="NCFS000" wn="04617562-n" >
  </token>
  <token id="t16.97" form="," lemma="," tag="Fc" >
  </token>
  <token id="t16.98" form="dans" lemma="dans" tag="SP" >
  </token>
  <token id="t16.99" form="le" lemma="le" tag="DA0MS0" >
  </token>
  <token id="t16.100" form="point" lemma="point" tag="NCMS000" wn="05865998-n" >
  </token>
  <token id="t16.101" form="visuel" lemma="visuel" tag="AQ0MS00" >
  </token>
  <token id="t16.102" form="." lemma="." tag="Fp" >
  </token>
  <token id="t16.103" form="--" lemma="--" tag="Fg" >
  </token>
  <token id="t16.104" form="Quant_à" lemma="quant_à" tag="SP" >
  </token>
  <token id="t16.105" form="la" lemma="le" tag="DA0FS0" >
  </token>
  <token id="t16.106" form="mobilité" lemma="mobilité" tag="NCFS000" wn="04773351-n" >
  </token>
  <token id="t16.107" form="de" lemma="de" tag="SP" >
  </token>
  <token id="t16.108" form="l&apos;" lemma="le" tag="DA0CS0" >
  </token>
  <token id="t16.109" form="oeil" lemma="œil" tag="NCMS000" wn="03442164-n" >
  </token>
  <token id="t16.110" form="lui-même" lemma="lui-même" tag="PP3MS00" >
  </token>
  <token id="t16.111" form="," lemma="," tag="Fc" >
  </token>
  <token id="t16.112" form="elle" lemma="elle" tag="PP3FS00" >
  </token>
  <token id="t16.113" form="résulte" lemma="résulter" tag="VMIP1S0" wn="02624263-v" >
  </token>
  <token id="t16.114" form="d&apos;" lemma="de" tag="SP" >
  </token>
  <token id="t16.115" form="invisibles" lemma="invisible" tag="NCMP000" >
  </token>
  <token id="t16.116" form="et" lemma="et" tag="CC" >
  </token>
  <token id="t16.117" form="presque" lemma="presque" tag="RG" wn="00073033-r" >
  </token>
  <token id="t16.118" form="nerveux" lemma="nerveux" tag="AQ0MN00" wn="02406370-a" >
  </token>
  <token id="t16.119" form="suspens" lemma="suspens" tag="NCMN000" >
  </token>
  <token id="t16.120" form="de" lemma="de" tag="SP" >
  </token>
  <token id="t16.121" form="le" lemma="le" tag="DA0MS0" >
  </token>
  <token id="t16.122" form="plus" lemma="plus" tag="RG" wn="00099341-r" >
  </token>
  <token id="t16.123" form="pur" lemma="pur" tag="AQ0MS00" wn="00361125-a" >
  </token>
  <token id="t16.124" form="acier" lemma="acier" tag="NCMS000" wn="14802450-n" >
  </token>
  <token id="t16.125" form="," lemma="," tag="Fc" >
  </token>
  <token id="t16.126" form="sur" lemma="sur" tag="SP" >
  </token>
  <token id="t16.127" form="lesquels" lemma="lequel" tag="PR0MP00" >
  </token>
  <token id="t16.128" form="il" lemma="il" tag="PP3MSN0" >
  </token>
  <token id="t16.129" form="tremble" lemma="trembler" tag="VMIP1S0" >
  </token>
  <token id="t16.130" form="," lemma="," tag="Fc" >
  </token>
  <token id="t16.131" form="glisse" lemma="glisser" tag="VMIP1S0" wn="01870275-v" >
  </token>
  <token id="t16.132" form="ou" lemma="ou" tag="CC" >
  </token>
  <token id="t16.133" form="demeure" lemma="demeurer" tag="VMIP1S0" wn="00117985-v" >
  </token>
  <token id="t16.134" form="immobile" lemma="immobile" tag="AQ0CS00" >
  </token>
  <token id="t16.135" form="selon" lemma="selon" tag="SP" >
  </token>
  <token id="t16.136" form="la" lemma="le" tag="DA0FS0" >
  </token>
  <token id="t16.137" form="dictée" lemma="dictée" tag="NCFS000" >
  </token>
  <token id="t16.138" form="de" lemma="de" tag="SP" >
  </token>
  <token id="t16.139" form="l&apos;" lemma="le" tag="DA0CS0" >
  </token>
  <token id="t16.140" form="Appareil-central_de_l&apos;_Andréïde" lemma="appareil-central_de_l&apos;_andréïde" tag="NP00000" >
  </token>
  <token id="t16.141" form="." lemma="." tag="Fp" >
  </token>
</sentence>
<sentence id="17">
  <token id="t17.1" form="Car" lemma="car" tag="CC" >
  </token>
  <token id="t17.2" form="le" lemma="le" tag="DA0MS0" >
  </token>
  <token id="t17.3" form="regard" lemma="regard" tag="NCMS000" wn="03717447-n" >
  </token>
  <token id="t17.4" form="," lemma="," tag="Fc" >
  </token>
  <token id="t17.5" form="le" lemma="le" tag="DA0MS0" >
  </token>
  <token id="t17.6" form="jeu" lemma="jeu" tag="NCMS000" wn="00455599-n" >
  </token>
  <token id="t17.7" form="de" lemma="de" tag="SP" >
  </token>
  <token id="t17.8" form="les" lemma="le" tag="DA0CP0" >
  </token>
  <token id="t17.9" form="paupières" lemma="paupière" tag="NCFP000" wn="05313822-n" >
  </token>
  <token id="t17.10" form="," lemma="," tag="Fc" >
  </token>
  <token id="t17.11" form="les" lemma="le" tag="DA0CP0" >
  </token>
  <token id="t17.12" form="paroles" lemma="parole" tag="NCFP000" >
  </token>
  <token id="t17.13" form="et" lemma="et" tag="CC" >
  </token>
  <token id="t17.14" form="le" lemma="le" tag="DA0MS0" >
  </token>
  <token id="t17.15" form="geste" lemma="geste" tag="NCCS000" wn="10771066-n" >
  </token>
  <token id="t17.16" form="y" lemma="y" tag="PP3CN00" >
  </token>
  <token id="t17.17" form="sont" lemma="être" tag="VSIP3P0" wn="02604760-v" >
  </token>
  <token id="t17.18" form="inscrits" lemma="inscrire" tag="VMP00PM" wn="01000214-v" >
  </token>
  <token id="t17.19" form="," lemma="," tag="Fc" >
  </token>
  <token id="t17.20" form="d" lemma="d" tag="AQ0MS0" >
  </token>
  <token id="t17.21" form="&apos;" lemma="&apos;" tag="Fe" >
  </token>
  <token id="t17.22" form="ensemble" lemma="ensemble" tag="NCMS000" wn="09513569-n" >
  </token>
  <token id="t17.23" form="," lemma="," tag="Fc" >
  </token>
  <token id="t17.24" form="comme" lemma="comme" tag="CS" >
  </token>
  <token id="t17.25" form="je" lemma="je" tag="PP1CSN0" >
  </token>
  <token id="t17.26" form="vous" lemma="vous" tag="PP2CP00" >
  </token>
  <token id="t17.27" form="l&apos;" lemma="le" tag="PP3CSA0" >
  </token>
  <token id="t17.28" form="ai" lemma="avoir" tag="VAIP1S0" wn="02604760-v" >
  </token>
  <token id="t17.29" form="dit" lemma="dire" tag="VMP00SM" >
  </token>
  <token id="t17.30" form="." lemma="." tag="Fp" >
  </token>
</sentence>
<sentence id="18">
  <token id="t18.1" form="Cela" lemma="cela" tag="PD0CS00" >
  </token>
  <token id="t18.2" form="ne" lemma="ne" tag="RN" >
  </token>
  <token id="t18.3" form="se" lemma="se" tag="PP3CN00" >
  </token>
  <token id="t18.4" form="voit" lemma="voir" tag="VMIP3S0" wn="02130160-v" >
  </token>
  <token id="t18.5" form="pas" lemma="pas" tag="RN" wn="00024073-r" >
  </token>
  <token id="t18.6" form="plus" lemma="plus" tag="RG" wn="00099341-r" >
  </token>
  <token id="t18.7" form="," lemma="," tag="Fc" >
  </token>
  <token id="t18.8" form="à" lemma="à" tag="SP" >
  </token>
  <token id="t18.9" form="l&apos;" lemma="le" tag="DA0CS0" >
  </token>
  <token id="t18.10" form="extérieur" lemma="extérieur" tag="NCMS000" wn="08613593-n" >
  </token>
  <token id="t18.11" form="," lemma="," tag="Fc" >
  </token>
  <token id="t18.12" form="que" lemma="que" tag="CS" >
  </token>
  <token id="t18.13" form="les" lemma="le" tag="DA0CP0" >
  </token>
  <token id="t18.14" form="réels" lemma="réel" tag="AQ0MP00" wn="00043765-a" >
  </token>
  <token id="t18.15" form="mobiles" lemma="mobile" tag="NCMP000" wn="02992529-n" >
  </token>
  <token id="t18.16" form="d&apos;" lemma="de" tag="SP" >
  </token>
  <token id="t18.17" form="un" lemma="un" tag="DI0MS0" >
  </token>
  <token id="t18.18" form="regard" lemma="regard" tag="NCMS000" wn="03717447-n" >
  </token>
  <token id="t18.19" form="sentimentalement" lemma="sentimentalement" tag="RG" >
  </token>
  <token id="t18.20" form="féminin" lemma="féminin" tag="AQ0MS00" >
  </token>
  <token id="t18.21" form="ne" lemma="ne" tag="RN" >
  </token>
  <token id="t18.22" form="transparaissent" lemma="transparaître" tag="VMIP3P0" >
  </token>
  <token id="t18.23" form="dans" lemma="dans" tag="SP" >
  </token>
  <token id="t18.24" form="l&apos;" lemma="le" tag="DA0CS0" >
  </token>
  <token id="t18.25" form="expression" lemma="expression" tag="NCFS000" wn="07139873-n" >
  </token>
  <token id="t18.26" form="apparente" lemma="apparent" tag="AQ0FS00" >
  </token>
  <token id="t18.27" form="." lemma="." tag="Fp" >
  </token>
</sentence>
<sentence id="19">
  <token id="t19.1" form="La" lemma="le" tag="DA0FS0" >
  </token>
  <token id="t19.2" form="carnation" lemma="carnation" tag="NCFS000" >
  </token>
  <token id="t19.3" form="," lemma="," tag="Fc" >
  </token>
  <token id="t19.4" form="la" lemma="le" tag="DA0FS0" >
  </token>
  <token id="t19.5" form="beauté" lemma="beauté" tag="NCFS000" >
  </token>
  <token id="t19.6" form="," lemma="," tag="Fc" >
  </token>
  <token id="t19.7" form="en" lemma="en" tag="PP3CN00" >
  </token>
  <token id="t19.8" form="adoucissent" lemma="adoucir" tag="VMIP3P0" >
  </token>
  <token id="t19.9" form="tout" lemma="tout" tag="DI0MS0" >
  </token>
  <token id="t19.10" form="le" lemma="le" tag="DA0MS0" >
  </token>
  <token id="t19.11" form="mécanisme" lemma="mécanisme" tag="NCMS000" wn="03183080-n" >
  </token>
  <token id="t19.12" form="dans" lemma="dans" tag="SP" >
  </token>
  <token id="t19.13" form="un" lemma="un" tag="DI0MS0" >
  </token>
  <token id="t19.14" form="fondu" lemma="fondu" tag="NCMS000" >
  </token>
  <token id="t19.15" form="idéal" lemma="idéal" tag="NCMS000" >
  </token>
  <token id="t19.16" form="." lemma="." tag="Fp" >
  </token>
</sentence>
<sentence id="20">
  <token id="t20.1" form="Une" lemma="un" tag="DI0FS0" >
  </token>
  <token id="t20.2" form="fois" lemma="fois" tag="NCFN000" >
  </token>
  <token id="t20.3" form="le" lemma="le" tag="DA0MS0" >
  </token>
  <token id="t20.4" form="travail" lemma="travail" tag="NCMS000" wn="00620752-n" >
  </token>
  <token id="t20.5" form="de" lemma="de" tag="SP" >
  </token>
  <token id="t20.6" form="les" lemma="le" tag="DA0CP0" >
  </token>
  <token id="t20.7" form="rectifications" lemma="rectification" tag="NCFP000" wn="13274092-n" >
  </token>
  <token id="t20.8" form="bien" lemma="bien" tag="RG" wn="00008007-r" >
  </token>
  <token id="t20.9" form="revu" lemma="revoir" tag="VMP00SM" >
  </token>
  <token id="t20.10" form="à" lemma="à" tag="SP" >
  </token>
  <token id="t20.11" form="le" lemma="le" tag="DA0MS0" >
  </token>
  <token id="t20.12" form="microscope" lemma="microscope" tag="NCMS000" wn="03760671-n" >
  </token>
  <token id="t20.13" form="," lemma="," tag="Fc" >
  </token>
  <token id="t20.14" form="ah" lemma="ah" tag="I" >
  </token>
  <token id="t20.15" form="!" lemma="!" tag="Fat" >
  </token>
  <token id="t20.16" form="par_exemple" lemma="par_exemple" tag="RG" wn="00159040-r" >
  </token>
  <token id="t20.17" form="!" lemma="!" tag="Fat" >
  </token>
  <token id="t20.18" form="vous" lemma="vous" tag="PP2CP00" >
  </token>
  <token id="t20.19" form="verrez" lemma="voir" tag="VMIF2P0" wn="02130160-v" >
  </token>
  <token id="t20.20" form="si" lemma="si" tag="CS" >
  </token>
  <token id="t20.21" form="je" lemma="je" tag="PP1CSN0" >
  </token>
  <token id="t20.22" form="ne" lemma="ne" tag="RN" >
  </token>
  <token id="t20.23" form="pourrai" lemma="pouvoir" tag="VMIF1S0" wn="02604760-v" >
  </token>
  <token id="t20.24" form="pas" lemma="pas" tag="RN" wn="00024073-r" >
  </token>
  <token id="t20.25" form="vous" lemma="vous" tag="PP2CP00" >
  </token>
  <token id="t20.26" form="défier" lemma="défier" tag="VMN0000" >
  </token>
  <token id="t20.27" form="," lemma="," tag="Fc" >
  </token>
  <token id="t20.28" form="mon" lemma="mon" tag="DP1CSS" >
  </token>
  <token id="t20.29" form="cher" lemma="cher" tag="AQ0MS00" wn="00933154-a" >
  </token>
  <token id="t20.30" form="lord" lemma="lord" tag="NCMS000" >
  </token>
  <token id="t20.31" form="," lemma="," tag="Fc" >
  </token>
  <token id="t20.32" form="de" lemma="de" tag="SP" >
  </token>
  <token id="t20.33" form="trouver" lemma="trouver" tag="VMN0000" wn="02154508-v" >
  </token>
  <token id="t20.34" form="plus_de" lemma="plus_de" tag="DI0CN0" >
  </token>
  <token id="t20.35" form="néant" lemma="néant" tag="NCMS000" >
  </token>
  <token id="t20.36" form="vivant" lemma="vivant" tag="AQ0MS00" wn="00806243-a" >
  </token>
  <token id="t20.37" form="dans" lemma="dans" tag="SP" >
  </token>
  <token id="t20.38" form="le" lemma="le" tag="DA0MS0" >
  </token>
  <token id="t20.39" form="regard" lemma="regard" tag="NCMS000" wn="03717447-n" >
  </token>
  <token id="t20.40" form="de" lemma="de" tag="SP" >
  </token>
  <token id="t20.41" form="miss" lemma="miss" tag="NCFN000" >
  </token>
  <token id="t20.42" form="Alicia_Clary" lemma="alicia_clary" tag="NP00000" >
  </token>
  <token id="t20.43" form="que" lemma="que" tag="CS" >
  </token>
  <token id="t20.44" form="dans" lemma="dans" tag="SP" >
  </token>
  <token id="t20.45" form="celui" lemma="celui" tag="PD0MS00" >
  </token>
  <token id="t20.46" form="de" lemma="de" tag="SP" >
  </token>
  <token id="t20.47" form="son" lemma="son" tag="DP3CSS" >
  </token>
  <token id="t20.48" form="fantôme" lemma="fantôme" tag="NCMS000" >
  </token>
  <token id="t20.49" form="!" lemma="!" tag="Fat" >
  </token>
</sentence>
<sentence id="21">
  <token id="t21.1" form="Et" lemma="et" tag="CC" >
  </token>
  <token id="t21.2" form="la" lemma="le" tag="DA0FS0" >
  </token>
  <token id="t21.3" form="beauté" lemma="beauté" tag="NCFS000" >
  </token>
  <token id="t21.4" form="éclatante" lemma="éclatant" tag="AQ0FS00" >
  </token>
  <token id="t21.5" form="de" lemma="de" tag="SP" >
  </token>
  <token id="t21.6" form="leurs" lemma="leur" tag="DP3CPP" >
  </token>
  <token id="t21.7" form="yeux" lemma="oeil" tag="NCMP000" >
  </token>
  <token id="t21.8" form="sera" lemma="être" tag="VSIF3S0" wn="02604760-v" >
  </token>
  <token id="t21.9" form="cependant" lemma="cependant" tag="RG" wn="00027384-r" >
  </token>
  <token id="t21.10" form="identique" lemma="identique" tag="AQ0CS00" wn="02068946-a" >
  </token>
  <token id="t21.11" form="." lemma="." tag="Fp" >
  </token>
</sentence>
